{
    "wallet": {
        "cogs": 33,
        "redCogs": 24,
        "blueCogs": 23,
        "purpleCogs": 23,
        "heartFragments": 23,
        "wings": 18,
        "eyes": 19,
        "chitins": 23,
        "fairyBreads": 14,
        "boxingGloves": 23,
        "hammers": 215
    },
    "maxHealth": 1,
    "powerLevel": 1,
    "difficulty": 2,
    "tempHealth": 0,
    "totalJumps": 4,
    "health": 1,
    "tunnelsBroken": {
        "tunnel1": true,
        "tunnel2": true,
        "tunnel3": true,
        "tunnel4": true,
        "tunnel5": true,
        "tunnel6": true
    },
    "deathCount": 46,
    "floors": {
        "normal": 1,
        "grass": 3,
        "spooky": 2,
        "rubiks": 3,
        "aussie": 21,
        "space": 6,
        "infinite": 1
    },
    "infiniteFloorMax": 7,
    "spawnPoint": [
        768,
        -528
    ],
    "enemyCountMax": 1,
    "mapSize": 15,
    "availableEnemyVariants": {
        "normal": [
            3
        ],
        "normalWeights": [
            2
        ],
        "grass": [
            3,
            9
        ],
        "grassWeights": [
            1,
            0.5
        ],
        "spooky": [
            3,
            13
        ],
        "spookyWeights": [
            1,
            1
        ],
        "rubiks": [
            3,
            15
        ],
        "rubiksWeights": [
            1,
            1
        ],
        "aussie": [
            3,
            20,
            19
        ],
        "aussieWeights": [
            1,
            2,
            2
        ],
        "space": [
            3,
            22
        ],
        "spaceWeights": [
            1,
            1
        ]
    },
    "screenshakeOn": true,
    "volumeOn": true,
    "portalsMet": {
        "lobby": true,
        "normal": true,
        "grass": true,
        "spooky": true,
        "rubiks": true,
        "aussie": true,
        "space": true,
        "infinite": true
    },
    "charactersMet": {
        "Hilbert": true,
        "Noether": false,
        "Curie": false,
        "Planck": false,
        "Faraday": true,
        "Lorenz": false,
        "Franklin": false,
        "Rubik": false,
        "Cantor": true,
        "Melatos": true,
        "Webster": true
    },
    "encountersCheck": {
        "spawnPoints": true,
        "heartAltars": true,
        "cogs": true,
        "redCogs": true,
        "blueCogs": false,
        "purpleCogs": true,
        "heartFragments": true,
        "wings": false,
        "eyes": true,
        "chitins": false,
        "fairyBreads": true,
        "boxingGloves": true,
        "hammers": false
    },
    "dialogue": {
        "Hilbert": {
            "0available": true,
            "0said": true,
            "1available": true,
            "1said": true,
            "2available": true,
            "2said": false,
            "3available": false,
            "3said": false,
            "4available": false,
            "4said": false,
            "5available": false,
            "5said": false,
            "6available": false,
            "6said": false,
            "7available": false,
            "7said": false,
            "8available": false,
            "8said": false,
            "9available": false,
            "9said": false
        },
        "Noether": {
            "0available": true,
            "0said": false,
            "1available": false,
            "1said": false,
            "2available": false,
            "2said": false,
            "3available": false,
            "3said": false,
            "4available": false,
            "4said": false,
            "5available": false,
            "5said": false
        },
        "Curie": {
            "0available": true,
            "0said": false,
            "1available": false,
            "1said": false,
            "2available": false,
            "2said": false,
            "3available": false,
            "3said": false,
            "4available": false,
            "4said": false
        },
        "Planck": {
            "0available": true,
            "0said": false,
            "1available": false,
            "1said": false,
            "2available": false,
            "2said": false
        },
        "Faraday": {
            "0available": true,
            "0said": true,
            "1available": true,
            "1said": true,
            "2available": true,
            "2said": true,
            "3available": true,
            "3said": false
        },
        "Lorenz": {
            "0available": true,
            "0said": false,
            "1available": false,
            "1said": false,
            "2available": false,
            "2said": false,
            "3available": false,
            "3said": false,
            "4available": false,
            "4said": false,
            "5available": false,
            "5said": false,
            "6available": false,
            "6said": false,
            "7available": false,
            "7said": false,
            "8available": false,
            "8said": false
        },
        "Franklin": {
            "0available": true,
            "0said": false,
            "1available": false,
            "1said": false,
            "2available": false,
            "2said": false,
            "3available": false,
            "3said": false,
            "4available": false,
            "4said": false
        },
        "Rubik": {
            "0available": true,
            "0said": false,
            "1available": false,
            "1said": false,
            "2available": false,
            "2said": false
        },
        "Cantor": {
            "0available": true,
            "0said": true,
            "1available": true,
            "1said": true,
            "2available": true,
            "2said": true,
            "3available": true,
            "3said": false
        },
        "Melatos": {
            "0available": true,
            "0said": true,
            "1available": true,
            "1said": true,
            "2available": true,
            "2said": true,
            "3available": true,
            "3said": true,
            "4available": true,
            "4said": true,
            "5available": true,
            "5said": true
        },
        "Webster": {
            "0available": true,
            "0said": true,
            "1available": true,
            "1said": true,
            "2available": true,
            "2said": true,
            "3available": true,
            "3said": true,
            "4available": true,
            "4said": true
        }
    }
}